setup.py
steam_market_helper/__init__.py
steam_market_helper/api_call.py
steam_market_helper/filter_funcs.py
steam_market_helper/funcs.py
steam_market_helper/parser.py
steam_market_helper/settings.py
steam_market_helper/smh.py
steam_market_helper/steam_market_helper_types.py
steammarkethelper.egg-info/PKG-INFO
steammarkethelper.egg-info/SOURCES.txt
steammarkethelper.egg-info/dependency_links.txt
steammarkethelper.egg-info/entry_points.txt
steammarkethelper.egg-info/requires.txt
steammarkethelper.egg-info/top_level.txt